odoo/addons/web_calendar_color_field/README.rst
odoo/addons/web_calendar_color_field/__init__.py
odoo/addons/web_calendar_color_field/__manifest__.py
odoo/addons/web_calendar_color_field/i18n/it.po
odoo/addons/web_calendar_color_field/i18n/web_calendar_color_field.pot
odoo/addons/web_calendar_color_field/readme/CONTRIBUTORS.rst
odoo/addons/web_calendar_color_field/readme/DESCRIPTION.rst
odoo/addons/web_calendar_color_field/readme/USAGE.rst
odoo/addons/web_calendar_color_field/static/description/icon.png
odoo/addons/web_calendar_color_field/static/description/index.html
odoo/addons/web_calendar_color_field/static/src/js/calendar.js
odoo/addons/web_calendar_color_field/views/assets.xml
odoo14_addon_web_calendar_color_field-14.0.1.0.1.dev7.dist-info/METADATA
odoo14_addon_web_calendar_color_field-14.0.1.0.1.dev7.dist-info/WHEEL
odoo14_addon_web_calendar_color_field-14.0.1.0.1.dev7.dist-info/top_level.txt
odoo14_addon_web_calendar_color_field-14.0.1.0.1.dev7.dist-info/RECORD
